{
  "name": "BLOCK-T646_2",
  "id": "afab1325-7c86-474c-bac1-978d126440cc",
  "program": "BLOCK-T646_2",
  "constraints": [],
  "scripts": [
    {
      "name": "run_command.py",
      "standard": true,
      "parameters": {
        "component": "CBP",
        "cmd": "move",
        "parameters": {
          "azimuth": -18.088108316442003,
          "elevation": -17.84563540079523
        }
      }
    },
    {
      "name": "maintel/point_azel.py",
      "standard": true,
      "parameters": {
        "az": -109.56886081587118,
        "el": 17.586501274055763,
        "target_name": "CBPCal",
        "ignore": [
          "mtdome",
          "mtdometrajectory"
        ]
      }
    },
    {
      "name": "run_command.py",
      "standard": true,
      "parameters": {
        "component": "Electrometer:101",
        "cmd": "startScanDt",
        "parameters": {
          "scanDuration": 1
        }
      }
    },
    {
      "name": "run_command.py",
      "standard": true,
      "parameters": {
        "component": "CBP",
        "cmd": "move",
        "parameters": {
          "azimuth": -18.084177647988895,
          "elevation": -17.83553908649361
        }
      }
    },
    {
      "name": "maintel/point_azel.py",
      "standard": true,
      "parameters": {
        "az": -109.62641655379605,
        "el": 17.67731091316159,
        "target_name": "CBPCal",
        "ignore": [
          "mtdome",
          "mtdometrajectory"
        ]
      }
    },
    {
      "name": "run_command.py",
      "standard": true,
      "parameters": {
        "component": "Electrometer:101",
        "cmd": "startScanDt",
        "parameters": {
          "scanDuration": 1
        }
      }
    },
    {
      "name": "run_command.py",
      "standard": true,
      "parameters": {
        "component": "CBP",
        "cmd": "move",
        "parameters": {
          "azimuth": -18.088226503983833,
          "elevation": -17.816070795832673
        }
      }
    },
    {
      "name": "maintel/point_azel.py",
      "standard": true,
      "parameters": {
        "az": -109.5695715399446,
        "el": 17.759060003538593,
        "target_name": "CBPCal",
        "ignore": [
          "mtdome",
          "mtdometrajectory"
        ]
      }
    },
    {
      "name": "run_command.py",
      "standard": true,
      "parameters": {
        "component": "Electrometer:101",
        "cmd": "startScanDt",
        "parameters": {
          "scanDuration": 1
        }
      }
    },
    {
      "name": "run_command.py",
      "standard": true,
      "parameters": {
        "component": "CBP",
        "cmd": "move",
        "parameters": {
          "azimuth": -18.092198114934035,
          "elevation": -17.796652175334742
        }
      }
    },
    {
      "name": "maintel/point_azel.py",
      "standard": true,
      "parameters": {
        "az": -109.51258941852143,
        "el": 17.840834551951502,
        "target_name": "CBPCal",
        "ignore": [
          "mtdome",
          "mtdometrajectory"
        ]
      }
    },
    {
      "name": "run_command.py",
      "standard": true,
      "parameters": {
        "component": "Electrometer:101",
        "cmd": "startScanDt",
        "parameters": {
          "scanDuration": 1
        }
      }
    },
    {
      "name": "run_command.py",
      "standard": true,
      "parameters": {
        "component": "CBP",
        "cmd": "move",
        "parameters": {
          "azimuth": -18.09609208798679,
          "elevation": -17.777283669530163
        }
      }
    },
    {
      "name": "maintel/point_azel.py",
      "standard": true,
      "parameters": {
        "az": -109.45547268603343,
        "el": 17.92263370033072,
        "target_name": "CBPCal",
        "ignore": [
          "mtdome",
          "mtdometrajectory"
        ]
      }
    },
    {
      "name": "run_command.py",
      "standard": true,
      "parameters": {
        "component": "Electrometer:101",
        "cmd": "startScanDt",
        "parameters": {
          "scanDuration": 1
        }
      }
    },
    {
      "name": "run_command.py",
      "standard": true,
      "parameters": {
        "component": "CBP",
        "cmd": "move",
        "parameters": {
          "azimuth": -18.103767947210827,
          "elevation": -17.76787812145426
        }
      }
    },
    {
      "name": "maintel/point_azel.py",
      "standard": true,
      "parameters": {
        "az": -109.34062030225755,
        "el": 17.91340489635121,
        "target_name": "CBPCal",
        "ignore": [
          "mtdome",
          "mtdometrajectory"
        ]
      }
    },
    {
      "name": "run_command.py",
      "standard": true,
      "parameters": {
        "component": "Electrometer:101",
        "cmd": "startScanDt",
        "parameters": {
          "scanDuration": 1
        }
      }
    },
    {
      "name": "run_command.py",
      "standard": true,
      "parameters": {
        "component": "CBP",
        "cmd": "move",
        "parameters": {
          "azimuth": -18.111376577039323,
          "elevation": -17.7584843103281
        }
      }
    },
    {
      "name": "maintel/point_azel.py",
      "standard": true,
      "parameters": {
        "az": -109.22571040821015,
        "el": 17.90411384545851,
        "target_name": "CBPCal",
        "ignore": [
          "mtdome",
          "mtdometrajectory"
        ]
      }
    },
    {
      "name": "run_command.py",
      "standard": true,
      "parameters": {
        "component": "Electrometer:101",
        "cmd": "startScanDt",
        "parameters": {
          "scanDuration": 1
        }
      }
    },
    {
      "name": "run_command.py",
      "standard": true,
      "parameters": {
        "component": "CBP",
        "cmd": "move",
        "parameters": {
          "azimuth": -18.1189179225305,
          "elevation": -17.749102466096332
        }
      }
    },
    {
      "name": "maintel/point_azel.py",
      "standard": true,
      "parameters": {
        "az": -109.11074573287294,
        "el": 17.894760897741662,
        "target_name": "CBPCal",
        "ignore": [
          "mtdome",
          "mtdometrajectory"
        ]
      }
    },
    {
      "name": "run_command.py",
      "standard": true,
      "parameters": {
        "component": "Electrometer:101",
        "cmd": "startScanDt",
        "parameters": {
          "scanDuration": 1
        }
      }
    },
    {
      "name": "run_command.py",
      "standard": true,
      "parameters": {
        "component": "CBP",
        "cmd": "move",
        "parameters": {
          "azimuth": -18.126391934734215,
          "elevation": -17.7397328161706
        }
      }
    },
    {
      "name": "maintel/point_azel.py",
      "standard": true,
      "parameters": {
        "az": -108.995729009647,
        "el": 17.885346416130062,
        "target_name": "CBPCal",
        "ignore": [
          "mtdome",
          "mtdometrajectory"
        ]
      }
    },
    {
      "name": "run_command.py",
      "standard": true,
      "parameters": {
        "component": "Electrometer:101",
        "cmd": "startScanDt",
        "parameters": {
          "scanDuration": 1
        }
      }
    },
    {
      "name": "run_command.py",
      "standard": true,
      "parameters": {
        "component": "CBP",
        "cmd": "move",
        "parameters": {
          "azimuth": -18.130383344154097,
          "elevation": -17.749723136153335
        }
      }
    },
    {
      "name": "maintel/point_azel.py",
      "standard": true,
      "parameters": {
        "az": -108.93848892637243,
        "el": 17.794238169665107,
        "target_name": "CBPCal",
        "ignore": [
          "mtdome",
          "mtdometrajectory"
        ]
      }
    },
    {
      "name": "run_command.py",
      "standard": true,
      "parameters": {
        "component": "Electrometer:101",
        "cmd": "startScanDt",
        "parameters": {
          "scanDuration": 1
        }
      }
    },
    {
      "name": "run_command.py",
      "standard": true,
      "parameters": {
        "component": "CBP",
        "cmd": "move",
        "parameters": {
          "azimuth": -18.134419977742937,
          "elevation": -17.75976816882283
        }
      }
    },
    {
      "name": "maintel/point_azel.py",
      "standard": true,
      "parameters": {
        "az": -108.88135599795959,
        "el": 17.70316045123269,
        "target_name": "CBPCal",
        "ignore": [
          "mtdome",
          "mtdometrajectory"
        ]
      }
    },
    {
      "name": "run_command.py",
      "standard": true,
      "parameters": {
        "component": "Electrometer:101",
        "cmd": "startScanDt",
        "parameters": {
          "scanDuration": 1
        }
      }
    },
    {
      "name": "run_command.py",
      "standard": true,
      "parameters": {
        "component": "CBP",
        "cmd": "move",
        "parameters": {
          "azimuth": -18.138501549916555,
          "elevation": -17.769867860848223
        }
      }
    },
    {
      "name": "maintel/point_azel.py",
      "standard": true,
      "parameters": {
        "az": -108.82433271728576,
        "el": 17.612114535488388,
        "target_name": "CBPCal",
        "ignore": [
          "mtdome",
          "mtdometrajectory"
        ]
      }
    },
    {
      "name": "run_command.py",
      "standard": true,
      "parameters": {
        "component": "Electrometer:101",
        "cmd": "startScanDt",
        "parameters": {
          "scanDuration": 1
        }
      }
    },
    {
      "name": "run_command.py",
      "standard": true,
      "parameters": {
        "component": "CBP",
        "cmd": "move",
        "parameters": {
          "azimuth": -18.142627770297395,
          "elevation": -17.780022157371576
        }
      }
    },
    {
      "name": "maintel/point_azel.py",
      "standard": true,
      "parameters": {
        "az": -108.76742157195736,
        "el": 17.52110169047461,
        "target_name": "CBPCal",
        "ignore": [
          "mtdome",
          "mtdometrajectory"
        ]
      }
    },
    {
      "name": "run_command.py",
      "standard": true,
      "parameters": {
        "component": "Electrometer:101",
        "cmd": "startScanDt",
        "parameters": {
          "scanDuration": 1
        }
      }
    },
    {
      "name": "run_command.py",
      "standard": true,
      "parameters": {
        "component": "CBP",
        "cmd": "move",
        "parameters": {
          "azimuth": -18.139183249038865,
          "elevation": -17.799557793227905
        }
      }
    },
    {
      "name": "maintel/point_azel.py",
      "standard": true,
      "parameters": {
        "az": -108.82517174040777,
        "el": 17.43968547198,
        "target_name": "CBPCal",
        "ignore": [
          "mtdome",
          "mtdometrajectory"
        ]
      }
    },
    {
      "name": "run_command.py",
      "standard": true,
      "parameters": {
        "component": "Electrometer:101",
        "cmd": "startScanDt",
        "parameters": {
          "scanDuration": 1
        }
      }
    },
    {
      "name": "run_command.py",
      "standard": true,
      "parameters": {
        "component": "CBP",
        "cmd": "move",
        "parameters": {
          "azimuth": -18.135660240801826,
          "elevation": -17.819142625352413
        }
      }
    },
    {
      "name": "maintel/point_azel.py",
      "standard": true,
      "parameters": {
        "az": -108.88279432634903,
        "el": 17.358302291785293,
        "target_name": "CBPCal",
        "ignore": [
          "mtdome",
          "mtdometrajectory"
        ]
      }
    },
    {
      "name": "run_command.py",
      "standard": true,
      "parameters": {
        "component": "Electrometer:101",
        "cmd": "startScanDt",
        "parameters": {
          "scanDuration": 1
        }
      }
    },
    {
      "name": "run_command.py",
      "standard": true,
      "parameters": {
        "component": "CBP",
        "cmd": "move",
        "parameters": {
          "azimuth": -18.132059118718985,
          "elevation": -17.83877619576336
        }
      }
    },
    {
      "name": "maintel/point_azel.py",
      "standard": true,
      "parameters": {
        "az": -108.94028680815046,
        "el": 17.276952969091212,
        "target_name": "CBPCal",
        "ignore": [
          "mtdome",
          "mtdometrajectory"
        ]
      }
    },
    {
      "name": "run_command.py",
      "standard": true,
      "parameters": {
        "component": "Electrometer:101",
        "cmd": "startScanDt",
        "parameters": {
          "scanDuration": 1
        }
      }
    },
    {
      "name": "run_command.py",
      "standard": true,
      "parameters": {
        "component": "CBP",
        "cmd": "move",
        "parameters": {
          "azimuth": -18.128380266384738,
          "elevation": -17.858458042595856
        }
      }
    },
    {
      "name": "maintel/point_azel.py",
      "standard": true,
      "parameters": {
        "az": -108.99764668481168,
        "el": 17.195638330849704,
        "target_name": "CBPCal",
        "ignore": [
          "mtdome",
          "mtdometrajectory"
        ]
      }
    },
    {
      "name": "run_command.py",
      "standard": true,
      "parameters": {
        "component": "Electrometer:101",
        "cmd": "startScanDt",
        "parameters": {
          "scanDuration": 1
        }
      }
    },
    {
      "name": "run_command.py",
      "standard": true,
      "parameters": {
        "component": "CBP",
        "cmd": "move",
        "parameters": {
          "azimuth": -18.120414780767305,
          "elevation": -17.86780928945589
        }
      }
    },
    {
      "name": "maintel/point_azel.py",
      "standard": true,
      "parameters": {
        "az": -109.11170461608265,
        "el": 17.205035629066316,
        "target_name": "CBPCal",
        "ignore": [
          "mtdome",
          "mtdometrajectory"
        ]
      }
    },
    {
      "name": "run_command.py",
      "standard": true,
      "parameters": {
        "component": "Electrometer:101",
        "cmd": "startScanDt",
        "parameters": {
          "scanDuration": 1
        }
      }
    }
  ]
}